{
  "en": {
    "appoinSalaryWithTable": "С помощью этого документа была создана таблица для сотрудника TableID:IDS."
  },
  "ru": {
    "100105": "Код ошибки - 100105: Нет доступа",
    "100109": "Невозможно редактировать",
    "100110": "Документ с таким кодом DocNumber уже существует",
    "100133": "Код ошибки - 100133: Неверный индекс...",
    "100134": "Начислено",
    "100135": "Удержано",
    "100136": "Итого:",
    "100137": "Сумма начислений не равен с суммой удержаний и суммой к выдаче",
    "100138": "Ушбу ҳужжатда ҳеч бир ходимга ҳисоблаш амалга оширилмаган",
    "100139": "Данный сотрудник не имеет основное место работы. EmployeeName",
    "100140": "Данный сотрудник уже имеет основное место работы. Выберите другой вид занятости. Например: Совмещение должностей EmployeeName",
    "100101": "Код ошибки - 100101: Для этого месяца уже рассчитана расчет",
    "100102": "Код ошибки - 100102: Существуют промежуточные расчеты. Отменить все промежуточные расчеты",
    "100103": "Код ошибки - 100103: У сотрудника EmployeeName сумма всех удержаний превышает сумму всех начислений",
    "100104": "Код ошибки - 100104: Для этого вида расчета уже рассчитана расчет",
    "100106": "Сотрудник удален",
    "100107": "Информация не найдена",
    "100108": "Код ошибки - 100108: Табель за полный месяц не найден",
    "100111": "Код ошибки - 100111: Лицевой счет, выбранный в документе, должен быть указан в табличной части",
    "100112": "Код ошибки - 100112: В табличной части документа для вида расчета следует указать процент",
    "100113": "Код ошибки - 100113: Документ приема на работу не найден",
    "100114": "Код ошибки - 100114: Дата приема сотрудника на работу не совпадает с датой документа",
    "100115": "Код ошибки - 100115: Для данного сотрудника Pinfl-FullName не создан документ \\\"Назначение зарплаты сотрудника\\\" соответствующий этой дате DocOn",
    "100116": "Процент должен быть в диапазоне от 0 до 100",
    "100117": "Код ошибки - 100117: Расчет зарплаты не указан",
    "100118": "Невозможно отправить документ. Статус документа неверный",
    "100119": "Платежное поручение не найдено",
    "100120": "Пластик карта с номером Key добавлен больше одного раза",
    "100121": "Платежные поручения не найден. Убедитесь, что статус документа проведено",
    "100122": "Дата платежного поручения неправильная",
    "100123": "Л/С реестра и Л/С платежного поручения не совпадают",
    "100124": "Сумма реестра и сумма платежного поручения не совпадают",
    "100125": "Неверный номер пластиковой карты. Employee PlasticCardNumber",
    "100126": "Employee Для этого сотрудника не указана сумма",
    "100127": "Код банка не выбран",
    "100128": "Ведомость (Пластик) за MonthOn не найден",
    "100129": "Расчет зарплата за MonthOn не найден",
    "100130": "При формировании заявки для аванса Дата документа и окно \"За месяц\" должны отражать текущий месяц",
    "100131": "Невозможно отправит документ. Статус документа неверный",
    "100132": "Для этого приказа на работу ранее была назначена зарплата  ДокИд:KeyId",
    "appoinSalaryWithTable": "С помощью этого документа была создана таблица для сотрудника TableID:IDS.",
    "SalaryCalcTemplate": "SalaryCalcTemplate_RUS.xlsm"
  },
  "uz_cyrl": {
    "100110": "DocNumber ушбу рақамли ҳужжат мавжуд",
    "100137": "Ушланма ва тўлов суммаси жами ҳисобланган суммага тенг эмас.",
    "100138": "Ушбу ходим аввал киритилган",
    "100139": "Ушбу ходимнинг асосий иш жойи йўқ EmployeeName",
    "100140": "Ушбу ходимнинг асосий иш жойи мавжуд. Бошқа бандлик турини танланг EmployeeName",
    "100101": "Код ошибки - 100101: Ушбу ой учун аввал ҳисоб-китоб қилинган",
    "100102": "Код ошибки - 100102: Оралиқ ҳисоб-китоблар мавжуд. Аввал уларни бекор қилинг",
    "100103": "Код ошибки - 100103: EmployeeName ушбу ходимдаги барча ушланмалар ҳисобланган суммадан ортиқ",
    "100104": "Код ошибки - 100104: Ушбу тўлов тури учун аввал ҳисоб-китоб қилинган",
    "100105": "Код ошибки - 100105: Рухсат берилмаган",
    "100106": "Ходим ўчириб юборилган",
    "100107": "Маълумот топилмади",
    "100108": "Код ошибки - 100108: Тўлиқ ой учун табель топилмади",
    "100109": "Таҳрирлаш мумкин эмас",
    "100111": "Код ошибки - 100111: Ушбу ҳужжатдаги тегишли ШҒҲ, ҳужжатнинг жадвал қисмида акс эттирилиши лозим",
    "100112": "Код ошибки - 100112: Тўлов турининг жадвал қисмида тегишли фоиз киритилиши керак",
    "100113": "Код ошибки - 100113: Ишга қабул қилиш ҳужжати топилмади",
    "100114": "Код ошибки - 100114: Ходимни ишга қабул қилинга сана ҳужжат санаси билан мос эмас",
    "100115": "Код ошибки - 100115: Pinfl-FullName ушбу ходимга DocOn санасида иш ҳақи бириктириш ҳужжати топилмади",
    "100116": "Фоиз миқдори 0 дан 100 оралиғида бўлиши керак",
    "100117": "Код ошибки - 100117: Ойлик ҳисоб-китоби кўрсатилмаган",
    "100118": "Ҳужжат ҳолати хато",
    "100119": "Тўлов топшириқнома топилмади",
    "100120": "Ушбу пластик карта рақами Key бир мартадан ортиқ кўрсатилган",
    "100121": "Тўлов топшириқнома топилмади. Ҳужжат ўтказилган ҳолатидалигини текширинг.",
    "100122": "Тўлов топшириқнома санаси хато",
    "100123": "Рўйхатдаги ШҒХ билан тўлов топшириқномасидаги ШҒХ мос эмас.",
    "100124": "Рўйхатдаги сумма билан тўлов топшириқномасидаги сумма мос эмас.",
    "100125": "Пластик карта рақами хато. Employee PlasticCardNumber",
    "100126": "Мазкур ходимда (Employee) сумма кўрсатилмаган",
    "100127": "Банк коди танланмаган",
    "100128": "MonthOn учун тўлов ҳужжати топмилмади.",
    "100129": "MonthOn учун ойлик ҳисоби топилмади.",
    "100130": "Аванс учун сўровнома шакллантиришда танланган ой Дата документа жорий ой бўлиши лозим.",
    "100131": "Ҳужжатни жўнатиб бўлмайди. Ҳужжат ҳолати хато.",
    "100132": "Мазкур буйруқ учун аввал иш ҳақи ҳисобланган.  Иш ҳақи ҳисоби ҳужжати ИД рақами:KeyId",
    "100133": "Хато коди - 100133: Индекс хато...",
    "100134": "Ҳисобланди",
    "100135": "Ушланди",
    "100136": "Жами:",
    "appoinSalaryWithTable": "Мазкур ҳужжат ёрдамида ходим учун табель ҳужжати яратилган. Аввал табельни ўчириш керак. Табель ҳужжати ИД рақами:IDS.",
    "SalaryCalcTemplate": "SalaryCalcTemplate_RUS.xlsm"
  },
  "uz_latn": {
    "100137": "Xatolik Kodi 100137: Maʼlumot topilmadi bank xodimlariga murojat qiling",
    "100138": "Ushbu xodim avval kiritilgan",
    "100139": "Ushbu xodimning asosiy ish joyi yoʼq  EmployeeName",
    "100140": "Ушбу ходимнинг асосий иш жойи мавжуд. Бошқа бандлик турини танланг EmployeeName",
    "100108": "Xatolik kodi - 100108: Табель за полный месяц не найден",
    "100132": "Ushbu qabul buyrug`i uchun ish haqi biriktirish hujjati avval yaratilgan DocID KeyId",
    "100133": "Xatolik kodi 100133:  Xato indeks...",
    "100134": "Hisoblandi",
    "100135": "Ushlandi",
    "100136": "Jami:",
    "appoinSalaryWithTable": "Ushbu hujjat orqali hodimga table yaratilgan TableID :IDS",
    "SalaryCalcTemplate": "SalaryCalcTemplate_LATN.xlsm"
  }
}